CHANGES
LICENSE
bootstrap.py
buildout.cfg
setup.cfg
setup.py
gp/__init__.py
gp.svndevelop.egg-info/PKG-INFO
gp.svndevelop.egg-info/SOURCES.txt
gp.svndevelop.egg-info/dependency_links.txt
gp.svndevelop.egg-info/entry_points.txt
gp.svndevelop.egg-info/namespace_packages.txt
gp.svndevelop.egg-info/not-zip-safe
gp.svndevelop.egg-info/requires.txt
gp.svndevelop.egg-info/top_level.txt
gp/svndevelop/README.txt
gp/svndevelop/__init__.py
gp/svndevelop/tests.py
