Metadata-Version: 1.0
Name: gp.svndevelop
Version: 0.4
Summary: ZC buildout extension to checkout develop eggs
Home-page: http://pypi.python.org/pypi/gp.svndevelop
Author: Gael Pasgrimaud
Author-email: gael@gawel.org
License: GPL
Keywords: buildout extension svn develop
Platform: UNKNOWN
Classifier: Framework :: Buildout
Classifier: Intended Audience :: Developers
Classifier: License :: OSI Approved
